README.md
setup.py
common/__init__.py
common/pb2/__init__.py
common/pb2/author_pb2.py
common/pb2/author_pb2_grpc.py
common/pb2/book_instance_pb2.py
common/pb2/book_instance_pb2_grpc.py
common/pb2/book_pb2.py
common/pb2/book_pb2_grpc.py
common/pb2/genre_pb2.py
common/pb2/genre_pb2_grpc.py
common/pb2/language_pb2.py
common/pb2/language_pb2_grpc.py
common/pb2/recommendations_pb2.py
common/pb2/recommendations_pb2_grpc.py
qservices_library.egg-info/PKG-INFO
qservices_library.egg-info/SOURCES.txt
qservices_library.egg-info/dependency_links.txt
qservices_library.egg-info/requires.txt
qservices_library.egg-info/top_level.txt